datacatalog_fileset_exporter/__init__.py
datacatalog_fileset_exporter/constant.py
datacatalog_fileset_exporter/datacatalog_facade.py
datacatalog_fileset_exporter/datacatalog_fileset_exporter_cli.py
datacatalog_fileset_exporter/fileset_datasource_exporter.py
datacatalog_fileset_exporter-0.2.3.dist-info/AUTHORS.rst
datacatalog_fileset_exporter-0.2.3.dist-info/LICENSE
datacatalog_fileset_exporter-0.2.3.dist-info/METADATA
datacatalog_fileset_exporter-0.2.3.dist-info/WHEEL
datacatalog_fileset_exporter-0.2.3.dist-info/entry_points.txt
datacatalog_fileset_exporter-0.2.3.dist-info/top_level.txt
datacatalog_fileset_exporter-0.2.3.dist-info/RECORD
